{
  "THEME": [
    { "image": "theme/theme1", "isAds": false ,"color":""},
    { "image": "theme/theme2", "isAds": false ,"color":""},
    { "image": "theme/theme3", "isAds": false ,"color":""},
    { "image": "theme/theme4", "isAds": false ,"color":""},
    { "image": "theme/theme5", "isAds": true ,"color":""},
    { "image": "theme/theme6", "isAds": true ,"color":""},
    { "image": "theme/theme7", "isAds": true,"color":"" },
    { "image": "theme/theme8", "isAds": true,"color":"" },
    { "image": "theme/theme9", "isAds": true ,"color":""},
    { "image": "theme/theme10", "isAds": true,"color":"" },
    { "image": "theme/theme11", "isAds": true,"color":"" },
    { "image": "theme/theme12", "isAds": true ,"color":""},
    { "image": "theme/theme13", "isAds": true ,"color":""},
    { "image": "theme/theme14", "isAds": true ,"color":""},
    { "image": "theme/theme15", "isAds": true,"color":"" },
    { "image": "theme/theme16", "isAds": true ,"color":""},
    { "image": "theme/theme17", "isAds": true ,"color":""},
    { "image": "theme/theme18", "isAds": true ,"color":""},
    { "image": "theme/theme19", "isAds": true ,"color":""},
    { "image": "theme/theme20", "isAds": true ,"color":""},
    { "image": "theme/theme21", "isAds": true ,"color":""},
    { "image": "theme/theme22", "isAds": true ,"color":""},
    { "image": "theme/theme23", "isAds": true,"color":"" },
    { "image": "theme/theme24", "isAds": true ,"color":""},
    { "image": "theme/theme25", "isAds": true ,"color":""},
    { "image": "theme/theme26", "isAds": true ,"color":""}
]

}