{
    "DATA": [
      {
        "id": 1,
        "core": "para1",
        "image": "para/para1",
        "_deltaTime": 4,
        "isAds": true
      },
      {
        "id": 2,
        "core": "para2",
        "image": "para/para2",
        "_deltaTime": 1.06,
        "isAds": true
      },
      {
        "id": 3,
        "core": "para3",
        "image": "para/para3",
        "_deltaTime": 0.9,
        "isAds": true
      },
      {
        "id": 4,
        "core": "para4",
        "image": "para/para4",
        "_deltaTime": 0.56,
        "isAds": true
      },
      {
        "id": 5,
        "core": "para5",
        "image": "para/para5",
        "_deltaTime": 0.9,
        "isAds": true
      },
      {
        "id": 6,
        "core": "para6",
        "image": "para/para6",
        "_deltaTime":0.9,
        "isAds": true
      },
      {
        "id": 7,
        "core": "para7",
        "image": "para/para7",
        "_deltaTime": 3,
        "isAds": true
      },
      {
        "id": 8,
        "core": "para8",
        "image": "para/para8",
        "_deltaTime": 5
        ,
        "isAds": true
      },
      {
        "id": 9,
        "core": "para9",
        "image": "para/para9",
        "_deltaTime":3,
        "isAds": true
      },
      {
        "id": 10,
        "core": "para10",
        "image": "para/para10",
        "_deltaTime": 3,
        "isAds": true
      },
      {
        "id": 11,
        "core": "para11",
        "image": "para/para11",
        "_deltaTime": 1.3,
        "isAds": true
      },
      {
        "id": 12,
        "core": "para12",
        "image": "para/para12",
        "_deltaTime": 0.9,
        "isAds": true
      },
      {
        "id": 13,
        "core": "para13",
        "image": "para/para13",
        "_deltaTime":0.6,
        "isAds": true
      },
      {
        "id": 14,
        "core": "para14",
        "image": "para/para14",
        "_deltaTime": 1.5,
        "isAds": true
      },
      {
        "id": 15,
        "core": "para15",
        "image": "para/para15",
        "_deltaTime": 3,
        "isAds": true
      },
      {
        "id": 16,
        "core": "para16",
        "image": "para/para16",
        "_deltaTime": 4.884,
        "isAds": true
      },
      {
        "id": 17,
        "core": "para17",
        "image": "para/para17",
        "_deltaTime":0.9,
        "isAds": true
      },
      {
        "id": 18,
        "core": "para18",
        "image": "para/para18",
        "_deltaTime": 3.6,
        "isAds": true
      },
      {
        "id": 19,
        "core": "para19",
        "image": "para/para19",
        "_deltaTime": 1.2,
        "isAds": true
      },
      {
        "id": 20,
        "core": "para20",
        "image": "para/para20",
        "_deltaTime": 1.2,
        "isAds": true
      },
      {
        "id": 21,
        "core": "para21",
        "image": "para/para21",
        "_deltaTime": 1.2,
        "isAds": true
      }

    ]
  }
  